dbt_mp/__init__.py
dbt_mp/main.py
dbt_mp-0.1.1.dist-info/licenses/LICENSE
dbt_mp-0.1.1.dist-info/METADATA
dbt_mp-0.1.1.dist-info/WHEEL
dbt_mp-0.1.1.dist-info/entry_points.txt
dbt_mp-0.1.1.dist-info/top_level.txt
dbt_mp-0.1.1.dist-info/RECORD
