Metadata-Version: 2.4
Name: dbt-mp
Version: 0.1.1
Summary: dbt-mp : dbt manifest parser for agentic context 
Requires-Python: >=3.10
License-File: LICENSE
Requires-Dist: python-semantic-release>=10.5.3
Dynamic: license-file
